README.md
setup.py
BeautifulReport/BeautifulReport.py
BeautifulReport/__init__.py
BeautifulReport.egg-info/PKG-INFO
BeautifulReport.egg-info/SOURCES.txt
BeautifulReport.egg-info/dependency_links.txt
BeautifulReport.egg-info/top_level.txt
BeautifulReport/template/template.html
BeautifulReport/template/theme.json
BeautifulReport/template/theme_candy.json
BeautifulReport/template/theme_cyan.json
BeautifulReport/template/theme_default.json
BeautifulReport/template/theme_memories.json