Metadata-Version: 2.1
Name: BeautifulReport
Version: 0.1.2
Summary: unittest自动化测试的可视化报告模板
Home-page: https://github.com/mocobk/BeautifulReport
Author: mocobk
Author-email: mocobk@163.com
License: UNKNOWN
Platform: UNKNOWN
Classifier: Programming Language :: Python :: 3
Classifier: License :: OSI Approved :: MIT License
Classifier: Operating System :: OS Independent
